{"assets":{"232242D33B01A60717AB72B38840B308":{"type":"texture","index":117,"assetRequest":{"type":"slide","state":"incoming","slide":"FB5E6AB0-D0F8-417C-A2CC-24D9CD69E188"},"url":"assets/232242D33B01A60717AB72B38840B308.svg","width":1024,"height":768},"6D5EA7589A0904100EE869194F9AE39B":{"type":"texture","index":116,"assetRequest":{"type":"slide","state":"outgoing","slide":"6F805573-7FFD-4109-8D37-EAD4A3A746FA"},"url":"assets/6D5EA7589A0904100EE869194F9AE39B.svg","width":1024,"height":768}},"events":[{"effects":[{"beginTime":0,"baseLayer":{"animations":[],"initialState":{"affineTransform":[1,0,0,1,0,0],"masksToBounds":true,"rotation":0,"scale":1,"position":{"pointX":512,"pointY":384},"width":1024,"sublayerTransform":[1,0,0,0,0,1,0,0,0,0,1,0,0,0,0,1],"contentsRect":{"y":0,"x":0,"width":1,"height":1},"opacity":1,"edgeAntialiasingMask":0,"height":768,"hidden":false,"anchorPoint":{"pointX":0.5,"pointY":0.5}},"objectID":"0","layers":[{"animations":[],"initialState":{"affineTransform":[1,0,0,1,0,0],"masksToBounds":false,"rotation":0,"scale":1,"position":{"pointX":512,"pointY":384},"width":1024,"sublayerTransform":[1,0,0,0,0,1,0,0,0,0,1,-0.0004922987690640373,0,0,0,1],"contentsRect":{"y":0,"x":0,"width":1,"height":1},"opacity":1,"edgeAntialiasingMask":15,"height":768,"hidden":false,"anchorPoint":{"pointX":0.5,"pointY":0.5}},"layers":[{"animations":[],"layers":[],"initialState":{"affineTransform":[1,0,0,1,0,0],"masksToBounds":false,"rotation":0,"scale":1,"position":{"pointX":512,"pointY":384},"width":1024,"sublayerTransform":[1,0,0,0,0,1,0,0,0,0,1,0,0,0,0,1],"contentsRect":{"y":0,"x":0,"width":1,"height":1},"opacity":1,"edgeAntialiasingMask":0,"height":768,"hidden":false,"anchorPoint":{"pointX":0.5,"pointY":0.5}},"texture":"232242D33B01A60717AB72B38840B308"},{"animations":[{"from":{"scalar":false},"beginTime":0,"repeatCount":0,"fillMode":"both","property":"hidden","duration":0.01,"to":{"scalar":true}}],"layers":[],"initialState":{"affineTransform":[1,0,0,1,0,0],"masksToBounds":false,"rotation":0,"scale":1,"position":{"pointX":512,"pointY":384},"width":1024,"sublayerTransform":[1,0,0,0,0,1,0,0,0,0,1,0,0,0,0,1],"contentsRect":{"y":0,"x":0,"width":1,"height":1},"opacity":1,"edgeAntialiasingMask":0,"height":768,"hidden":false,"anchorPoint":{"pointX":0.5,"pointY":0.5}},"texture":"6D5EA7589A0904100EE869194F9AE39B"}]}]},"effects":[],"duration":0.01,"type":"transition","name":"none","objectID":"0"}],"automaticPlay":false,"hyperlinks":[],"accessibility":[{"text":"pasted-image.pdf","targetRectangle":{"y":45.74607467651367,"x":197.4026641845703,"width":135.861328125,"height":135.861328125}},{"text":"pasted-image.png","targetRectangle":{"y":414.5296325683594,"x":703.0693359375,"width":300,"height":224}},{"text":"Trumpgram","targetRectangle":{"y":69.99999976158142,"x":396.5750017166138,"width":230.85,"height":54}},{"text":"pasted-image.png","targetRectangle":{"y":207.9451141357422,"x":634,"width":162.1749267578125,"height":190.0548858642578}},{"text":"#DevFestGRX","targetRectangle":{"y":735.9159852266312,"x":848.3207218647003,"width":169.0640000000001,"height":33.18780517578125}},{"text":"pasted-image.png","targetRectangle":{"y":260.2796325683594,"x":406,"width":174,"height":310}},{"text":"pasted-image.tif","targetRectangle":{"y":655.0592651367188,"x":0,"width":1024,"height":113.8814926147461}},{"text":"pasted-image.tif","targetRectangle":{"y":337,"x":96,"width":256,"height":256}},{"text":"pasted-image.png","targetRectangle":{"y":126.1488952636719,"x":638,"width":256,"height":128}},{"text":"pasted-image.png","targetRectangle":{"y":-550.6666870117188,"x":-2,"width":1028,"height":577.9644775390625}},{"text":"pasted-image.png","targetRectangle":{"y":601.2409057617188,"x":836.9125366210938,"width":162.1749267578125,"height":54.81512451171875}}],"baseLayer":{"animations":[],"initialState":{"affineTransform":[1,0,0,1,0,0],"masksToBounds":true,"rotation":0,"scale":1,"position":{"pointX":512,"pointY":384},"width":1024,"sublayerTransform":[1,0,0,0,0,1,0,0,0,0,1,0,0,0,0,1],"contentsRect":{"y":0,"x":0,"width":1,"height":1},"opacity":1,"edgeAntialiasingMask":0,"height":768,"hidden":false,"anchorPoint":{"pointX":0.5,"pointY":0.5}},"objectID":"0","layers":[{"animations":[],"initialState":{"affineTransform":[1,0,0,1,0,0],"masksToBounds":false,"rotation":0,"scale":1,"position":{"pointX":512,"pointY":384},"width":1024,"sublayerTransform":[1,0,0,0,0,1,0,0,0,0,1,-0.0004922987690640373,0,0,0,1],"contentsRect":{"y":0,"x":0,"width":1,"height":1},"opacity":1,"edgeAntialiasingMask":15,"height":768,"hidden":false,"anchorPoint":{"pointX":0.5,"pointY":0.5}},"layers":[{"animations":[],"layers":[],"initialState":{"affineTransform":[1,0,0,1,0,0],"masksToBounds":false,"rotation":0,"scale":1,"position":{"pointX":512,"pointY":384},"width":1024,"sublayerTransform":[1,0,0,0,0,1,0,0,0,0,1,0,0,0,0,1],"contentsRect":{"y":0,"x":0,"width":1,"height":1},"opacity":1,"edgeAntialiasingMask":0,"height":768,"hidden":false,"anchorPoint":{"pointX":0.5,"pointY":0.5}},"texture":"6D5EA7589A0904100EE869194F9AE39B"}]}]}}]}